NiukeKehuduanGangQiuzhiJingyanFenxiang20212022/README.md
NiukeKehuduanGangQiuzhiJingyanFenxiang20212022/__init__.py
NiukeKehuduanGangQiuzhiJingyanFenxiang20212022/__main__.py
NiukeKehuduanGangQiuzhiJingyanFenxiang20212022/file.epub
NiukeKehuduanGangQiuzhiJingyanFenxiang20212022/index.html
NiukeKehuduanGangQiuzhiJingyanFenxiang20212022/css/__init__.py
NiukeKehuduanGangQiuzhiJingyanFenxiang20212022/css/annotations.css
NiukeKehuduanGangQiuzhiJingyanFenxiang20212022/css/main.css
NiukeKehuduanGangQiuzhiJingyanFenxiang20212022/css/normalize.css
NiukeKehuduanGangQiuzhiJingyanFenxiang20212022/css/popup.css
NiukeKehuduanGangQiuzhiJingyanFenxiang20212022/font/__init__.py
NiukeKehuduanGangQiuzhiJingyanFenxiang20212022/font/fontello.eot
NiukeKehuduanGangQiuzhiJingyanFenxiang20212022/font/fontello.svg
NiukeKehuduanGangQiuzhiJingyanFenxiang20212022/font/fontello.ttf
NiukeKehuduanGangQiuzhiJingyanFenxiang20212022/font/fontello.woff
NiukeKehuduanGangQiuzhiJingyanFenxiang20212022/img/__init__.py
NiukeKehuduanGangQiuzhiJingyanFenxiang20212022/img/annotator-glyph-sprite.png
NiukeKehuduanGangQiuzhiJingyanFenxiang20212022/img/annotator-icon-sprite.png
NiukeKehuduanGangQiuzhiJingyanFenxiang20212022/img/apple-touch-icon.png
NiukeKehuduanGangQiuzhiJingyanFenxiang20212022/img/cancelfullscreen.png
NiukeKehuduanGangQiuzhiJingyanFenxiang20212022/img/close.png
NiukeKehuduanGangQiuzhiJingyanFenxiang20212022/img/fullscreen.png
NiukeKehuduanGangQiuzhiJingyanFenxiang20212022/img/loader.gif
NiukeKehuduanGangQiuzhiJingyanFenxiang20212022/img/menu-icon.png
NiukeKehuduanGangQiuzhiJingyanFenxiang20212022/img/save.png
NiukeKehuduanGangQiuzhiJingyanFenxiang20212022/img/saved.png
NiukeKehuduanGangQiuzhiJingyanFenxiang20212022/img/settings-s.png
NiukeKehuduanGangQiuzhiJingyanFenxiang20212022/img/settings.png
NiukeKehuduanGangQiuzhiJingyanFenxiang20212022/img/star.png
NiukeKehuduanGangQiuzhiJingyanFenxiang20212022/js/__init__.py
NiukeKehuduanGangQiuzhiJingyanFenxiang20212022/js/epub.js
niuke_kehuduan_gang_qiuzhi_jingyan_fenxiang_2021_2022-2024.3.6.0.dist-info/METADATA
niuke_kehuduan_gang_qiuzhi_jingyan_fenxiang_2021_2022-2024.3.6.0.dist-info/WHEEL
niuke_kehuduan_gang_qiuzhi_jingyan_fenxiang_2021_2022-2024.3.6.0.dist-info/entry_points.txt
niuke_kehuduan_gang_qiuzhi_jingyan_fenxiang_2021_2022-2024.3.6.0.dist-info/top_level.txt
niuke_kehuduan_gang_qiuzhi_jingyan_fenxiang_2021_2022-2024.3.6.0.dist-info/RECORD
